mindspore_lite/.commit_id
mindspore_lite/__init__.py
mindspore_lite/_checkparam.py
mindspore_lite/context.py
mindspore_lite/converter.py
mindspore_lite/model.py
mindspore_lite/tensor.py
mindspore_lite/version.py
mindspore_lite/include/api/allocator.h
mindspore_lite/include/api/cell.h
mindspore_lite/include/api/cfg.h
mindspore_lite/include/api/context.h
mindspore_lite/include/api/data_type.h
mindspore_lite/include/api/delegate.h
mindspore_lite/include/api/delegate_api.h
mindspore_lite/include/api/dual_abi_helper.h
mindspore_lite/include/api/format.h
mindspore_lite/include/api/graph.h
mindspore_lite/include/api/kernel.h
mindspore_lite/include/api/kernel_api.h
mindspore_lite/include/api/model.h
mindspore_lite/include/api/model_group.h
mindspore_lite/include/api/model_parallel_runner.h
mindspore_lite/include/api/net.h
mindspore_lite/include/api/serialization.h
mindspore_lite/include/api/status.h
mindspore_lite/include/api/types.h
mindspore_lite/include/api/visible.h
mindspore_lite/include/api/callback/callback.h
mindspore_lite/include/api/callback/ckpt_saver.h
mindspore_lite/include/api/callback/loss_monitor.h
mindspore_lite/include/api/callback/lr_scheduler.h
mindspore_lite/include/api/callback/time_monitor.h
mindspore_lite/include/api/callback/train_accuracy.h
mindspore_lite/include/api/metrics/accuracy.h
mindspore_lite/include/api/metrics/metrics.h
mindspore_lite/include/mindapi/base/format.h
mindspore_lite/include/mindapi/base/type_id.h
mindspore_lite/include/mindapi/base/types.h
mindspore_lite/include/registry/converter_context.h
mindspore_lite/lib/_c_lite_wrapper.cpython-37m-aarch64-linux-gnu.so
mindspore_lite/lib/libascend_kernel_plugin_python.so
mindspore_lite/lib/libascend_pass_plugin.so
mindspore_lite/lib/libdvpp_utils.so
mindspore_lite/lib/liblite-unified-executor.so
mindspore_lite/lib/libmindspore-extendrt_python.so
mindspore_lite/lib/libmindspore_converter.so
mindspore_lite/lib/libmindspore_core.so
mindspore_lite/lib/libmindspore_glog.so.0
mindspore_lite-2.0.0.dist-info/METADATA
mindspore_lite-2.0.0.dist-info/WHEEL
mindspore_lite-2.0.0.dist-info/top_level.txt
mindspore_lite-2.0.0.dist-info/RECORD
